crispum/__init__.py
crispum/conditional.py
crispum/philter.py
crispum/pluck.py
crispum/simple.py
crispum-0.2.0.dist-info/DESCRIPTION.rst
crispum-0.2.0.dist-info/METADATA
crispum-0.2.0.dist-info/RECORD
crispum-0.2.0.dist-info/WHEEL
crispum-0.2.0.dist-info/metadata.json
crispum-0.2.0.dist-info/top_level.txt
