Metadata-Version: 2.0
Name: crispum
Version: 0.2.0
Summary: Declarative JSON data parsing pipeline
Home-page: https://github.com/chrisinajar/crispum
Author: Chris Vickery
Author-email: chrisinajar@gmail.com
License: MIT
Platform: UNKNOWN
Requires-Dist: dot-prop (>=0.2.0)
Requires-Dist: obstruction (>=0.1.1)
Requires-Dist: six (>=1.10)
